mcp_autogui/__init__.py
mcp_autogui/mcp_autogui_main.py
mcp_autogui/langchain/agent_graph.py
mcp_autogui/langchain/mcp_manager.py
omniparserserver/__init__.py
mseep_omniparser_autogui_mcp-0.1.1.dist-info/METADATA
mseep_omniparser_autogui_mcp-0.1.1.dist-info/WHEEL
mseep_omniparser_autogui_mcp-0.1.1.dist-info/entry_points.txt
mseep_omniparser_autogui_mcp-0.1.1.dist-info/licenses/LICENSE
mseep_omniparser_autogui_mcp-0.1.1.dist-info/RECORD
