Metadata-Version: 2.4
Name: mseep-omniparser-autogui-mcp
Version: 0.1.1
Summary: Automatic operation of on-screen GUI.
Author-email: mseep <support@skydeck.ai>
License: MIT License
License-File: LICENSE
Requires-Python: >=3.12
Requires-Dist: accelerate>=1.4.0
Requires-Dist: anthropic[bedrock,vertex]>=0.37.1
Requires-Dist: azure-identity>=1.20.0
Requires-Dist: boto3>=1.28.57
Requires-Dist: dashscope>=1.22.1
Requires-Dist: dill>=0.3.9
Requires-Dist: easyocr>=1.7.2
Requires-Dist: einops==0.8.0
Requires-Dist: google-auth<3,>=2
Requires-Dist: gradio>=5.13.2
Requires-Dist: groq>=0.18.0
Requires-Dist: jsonschema==4.22.0
Requires-Dist: mcp[cli]>=1.3.0
Requires-Dist: numpy==1.26.4
Requires-Dist: openai>=1.58.1
Requires-Dist: opencv-python-headless>=4.11.0.86
Requires-Dist: opencv-python>=4.11.0.86
Requires-Dist: paddleocr>=2.9.1
Requires-Dist: paddlepaddle>=2.6.2
Requires-Dist: pandas>=2.2.3
Requires-Dist: pre-commit==3.8.0
Requires-Dist: pyautogui==0.9.54
Requires-Dist: pyperclip>=1.9.0
Requires-Dist: pytest-asyncio==0.23.6
Requires-Dist: pytest==8.3.3
Requires-Dist: requests>=2.32.3
Requires-Dist: ruff==0.6.7
Requires-Dist: screeninfo>=0.8.1
Requires-Dist: setuptools>=75.6.0
Requires-Dist: streamlit>=1.38.0
Requires-Dist: supervision==0.18.0
Requires-Dist: timm>=1.0.14
Requires-Dist: torch>=2.6.0
Requires-Dist: torchvision>=0.21.0
Requires-Dist: transformers>=4.49.0
Requires-Dist: uiautomation>=2.0.20
Requires-Dist: ultralytics==8.3.70
Requires-Dist: uvicorn>=0.34.0
Provides-Extra: langchain
Requires-Dist: langchain; extra == 'langchain'
Requires-Dist: langchain-community; extra == 'langchain'
Requires-Dist: langchain-google-genai; extra == 'langchain'
Requires-Dist: langchain-mcp; extra == 'langchain'
Requires-Dist: langchain-openai>=0.3.6; extra == 'langchain'
Requires-Dist: langgraph; extra == 'langchain'
